stable_codec/__init__.py
stable_codec/ctc_loss.py
stable_codec/fsq.py
stable_codec/model.py
stable_codec/residual_fsq.py
stable_codec/training_demo.py
stable_codec/training_module.py
stable_codec-0.1.2.dist-info/LICENSE
stable_codec-0.1.2.dist-info/METADATA
stable_codec-0.1.2.dist-info/WHEEL
stable_codec-0.1.2.dist-info/top_level.txt
stable_codec-0.1.2.dist-info/RECORD
