Metadata-Version: 2.2
Name: stable-codec
Version: 0.1.2
Summary: Stable Codec: A series of codec models for speech and audio
Home-page: https://github.com/Stability-AI/stable-codec/
Author: Stability AI
Author-email: julian.parker@stability.ai
Requires-Python: >=3.9
License-File: LICENSE
Requires-Dist: packaging
Requires-Dist: wheel
Requires-Dist: torch==2.4
Requires-Dist: torchaudio==2.4
Requires-Dist: stable-audio-tools==0.0.17
Requires-Dist: pytorch-lightning==2.1
Requires-Dist: prefigure==0.0.9
Dynamic: author
Dynamic: author-email
Dynamic: description
Dynamic: description-content-type
Dynamic: home-page
Dynamic: requires-dist
Dynamic: requires-python
Dynamic: summary
